{"settings":[{"key":"App_Version","valueType":"string","defaultValue":"0.00-0","configTitle":"App_Version_Title","configPrompt":null,"configType":"alphaNumeric","configError":null,"configHelpUrl":null,"configReadonly":true,"configRequired":false,"configOptions":null,"configMin":null,"configMax":null,"configMaxLength":null},{"key":"Field_Time_Duration","valueType":"number","defaultValue":2,"configTitle":"Field_Time_Duration_Title","configPrompt":null,"configType":"numeric","configError":null,"configHelpUrl":null,"configReadonly":false,"configRequired":false,"configOptions":null,"configMin":0,"configMax":10,"configMaxLength":null},{"key":"Field_Timer_Duration","valueType":"number","defaultValue":2,"configTitle":"Field_Timer_Duration_Title","configPrompt":null,"configType":"numeric","configError":null,"configHelpUrl":null,"configReadonly":false,"configRequired":false,"configOptions":null,"configMin":0,"configMax":10,"configMaxLength":null},{"key":"Field_Distance_Duration","valueType":"number","defaultValue":2,"configTitle":"Field_Distance_Duration_Title","configPrompt":null,"configType":"numeric","configError":null,"configHelpUrl":null,"configReadonly":false,"configRequired":false,"configOptions":null,"configMin":0,"configMax":10,"configMaxLength":null},{"key":"Field_TimeOfDay_Duration","valueType":"number","defaultValue":2,"configTitle":"Field_TimeOfDay_Duration_Title","configPrompt":null,"configType":"numeric","configError":null,"configHelpUrl":null,"configReadonly":false,"configRequired":false,"configOptions":null,"configMin":0,"configMax":10,"configMaxLength":null},{"key":"Field_DistanceToDestination_Duration","valueType":"number","defaultValue":2,"configTitle":"Field_DistanceToDestination_Duration_Title","configPrompt":null,"configType":"numeric","configError":null,"configHelpUrl":null,"configReadonly":false,"configRequired":false,"configOptions":null,"configMin":0,"configMax":10,"configMaxLength":null}],"supportsLiveValidation":false,"languages":{"valyrian":{"Field_Distance_Duration_Title":"Distance field duration","DF_Title_Title":"Data Field Title","Field_Timer_Label_Title":"Timer","Device":"???","Field_Time_Label_Title":"Time","Field_Timer_Duration_Title":"Timer field duration","Field_Time_Duration_Title":"Time field duration","Field_TimeOfDay_Duration_Title":"Time of Day duration","Field_DistanceToDestination_Label_Title":"Dist. to Dest.","App_Version_Title":"Application Version","Field_Distance_Label_Title":"Distance","AppName":"DF_RollingField","Field_DistanceToDestination_Duration_Title":"Distance to Destination duration","AppVersion":"1.24-3","Field_TimeOfDay_Label_Title":"Time of Day","Support_distanceToDestination":"yes"}}}